LICENSE.txt
MANIFEST.in
README.md
pyproject.toml
setup.cfg
src/on_the_fly_stats/__init__.py
src/on_the_fly_stats/average_info.py
src/on_the_fly_stats/build_info.py
src/on_the_fly_stats/constants_version.py
src/on_the_fly_stats/counter_info.py
src/on_the_fly_stats/min_max_info.py
src/on_the_fly_stats/otf_stats.py
src/on_the_fly_stats/stddev_info.py
src/on_the_fly_stats.egg-info/PKG-INFO
src/on_the_fly_stats.egg-info/SOURCES.txt
src/on_the_fly_stats.egg-info/dependency_links.txt
src/on_the_fly_stats.egg-info/requires.txt
src/on_the_fly_stats.egg-info/top_level.txt