Metadata-Version: 2.4
Name: on-the-fly-stats
Version: 1.2.2
Summary: On the fly statistics including standard deviation, average, min/max and counters
Author-email: "J. Arrizza" <cppgent0@gmail.com>
Maintainer-email: "J. Arrizza" <cppgent0@gmail.com>
License-Expression: MIT
Project-URL: Website, https://arrizza.com/python-on-the-fly-stats
Project-URL: Source, https://bitbucket.org/arrizza-public/on-the-fly-stats/src/master
Project-URL: Download, https://bitbucket.org/arrizza-public/on-the-fly-stats/get/master.zip
Keywords: statistics,utility
Classifier: Development Status :: 5 - Production/Stable
Classifier: Environment :: Console
Classifier: Topic :: Utilities
Classifier: Intended Audience :: Developers
Classifier: Programming Language :: Python :: 3.10
Classifier: Programming Language :: Python :: 3.12
Requires-Python: >=3.9
License-File: LICENSE.txt
Requires-Dist: falcon-logger
Dynamic: license-file
